foveator/__init__.py
foveator/parse.py
foveator-0.1.dist-info/DESCRIPTION.rst
foveator-0.1.dist-info/METADATA
foveator-0.1.dist-info/RECORD
foveator-0.1.dist-info/WHEEL
foveator-0.1.dist-info/metadata.json
foveator-0.1.dist-info/top_level.txt
