Metadata-Version: 2.0
Name: foveator
Version: 0.1
Summary: A package for dealing with fovea output
Home-page: https://github.com/josephbb/foveator
Author: Joseph Bak-Coleman
Author-email: jbakcoleman@gmail.com
License: UNKNOWN
Platform: UNKNOWN
